pdf2png/__init__.py
pdf2png/__main__.py
pdf2png/_version.py
pdf2png/py.typed
pdf2png-1.0.0.dist-info/LICENSE
pdf2png-1.0.0.dist-info/METADATA
pdf2png-1.0.0.dist-info/WHEEL
pdf2png-1.0.0.dist-info/entry_points.txt
pdf2png-1.0.0.dist-info/top_level.txt
pdf2png-1.0.0.dist-info/RECORD
