Metadata-Version: 2.2
Name: pdf2png
Version: 1.0.0
Summary: CLI utility to convert PDF pages to PNG images
Author-email: Ryan Kozak <ReK42@users.noreply.github.com>
Maintainer-email: Ryan Kozak <ReK42@users.noreply.github.com>
License:                     GNU GENERAL PUBLIC LICENSE
Project-URL: Repository, https://github.com/ReK42/pdf2png
Project-URL: Issues, https://github.com/ReK42/pdf2png/issues
Classifier: Development Status :: 3 - Alpha
Classifier: License :: OSI Approved :: GNU General Public License v3 (GPLv3)
Classifier: Natural Language :: English
Classifier: Operating System :: OS Independent
Classifier: Programming Language :: Python
Classifier: Programming Language :: Python :: 3
Classifier: Programming Language :: Python :: 3 :: Only
Classifier: Programming Language :: Python :: 3.9
Classifier: Programming Language :: Python :: 3.10
Classifier: Programming Language :: Python :: 3.11
Classifier: Programming Language :: Python :: 3.12
Classifier: Programming Language :: Python :: 3.13
Classifier: Typing :: Typed
Requires-Python: >=3.9
License-File: LICENSE
Requires-Dist: click==8.1.8
Requires-Dist: rich==13.9.4
Requires-Dist: pypdf==5.1.0
Requires-Dist: Wand==0.6.13
Provides-Extra: test
Requires-Dist: mypy==1.14.1; extra == "test"
Requires-Dist: ruff==0.9.3; extra == "test"
Provides-Extra: build
Requires-Dist: setuptools==75.8.0; extra == "build"
Requires-Dist: setuptools-scm==8.1.0; extra == "build"
Requires-Dist: build==1.2.2.post1; extra == "build"
Requires-Dist: twine==6.1.0; extra == "build"
